ByteBird/__init__.py
ByteBird/__main__.py
ByteBird/game.py
7seg_ByteBird-0.2.dist-info/LICENSE
7seg_ByteBird-0.2.dist-info/METADATA
7seg_ByteBird-0.2.dist-info/WHEEL
7seg_ByteBird-0.2.dist-info/entry_points.txt
7seg_ByteBird-0.2.dist-info/top_level.txt
7seg_ByteBird-0.2.dist-info/RECORD
